datakleaner/__init__.py
datakleaner/diagnosis.py
datakleaner/duplicates.py
datakleaner/missing_data.py
datakleaner/outliers.py
datakleaner-0.1.1.dist-info/LICENCE
datakleaner-0.1.1.dist-info/LICENSE
datakleaner-0.1.1.dist-info/METADATA
datakleaner-0.1.1.dist-info/WHEEL
datakleaner-0.1.1.dist-info/top_level.txt
datakleaner-0.1.1.dist-info/RECORD
