Metadata-Version: 2.2
Name: datakleaner
Version: 0.1.1
Summary: An open-source Python package for checking and handling missing data, duplicates, and outliers in datasets.
Author-email: David Ahonsu <olivetahonsu@gmail.com>
License: Apache-2.0
Project-URL: Homepage, https://github.com/olivetahonsu/datakleaner
Project-URL: Repository, https://github.com/olivetahonsu/datakleaner.git
Project-URL: Issues, https://github.com/olivetahonsu/datakleaner/issues
Classifier: Development Status :: 4 - Beta
Classifier: License :: OSI Approved :: Apache Software License
Classifier: Programming Language :: Python :: 3
Classifier: Topic :: Scientific/Engineering :: Information Analysis
Classifier: Topic :: Software Development :: Libraries :: Python Modules
Classifier: Operating System :: OS Independent
Classifier: Intended Audience :: End Users/Desktop
Classifier: Intended Audience :: Information Technology
Classifier: Intended Audience :: Developers
Classifier: Intended Audience :: Science/Research
Classifier: Intended Audience :: Other Audience
Requires-Python: >=3.0
License-File: LICENCE
License-File: LICENSE
Requires-Dist: pandas
Requires-Dist: numpy
Requires-Dist: matplotlib
Requires-Dist: scipy
